nuru_clock/__init__.py
nuru_clock/__main__.py
nuru_clock-0.1.0.dist-info/licenses/LICENSE
nuru_clock-0.1.0.dist-info/METADATA
nuru_clock-0.1.0.dist-info/WHEEL
nuru_clock-0.1.0.dist-info/entry_points.txt
nuru_clock-0.1.0.dist-info/top_level.txt
nuru_clock-0.1.0.dist-info/RECORD
