Metadata-Version: 2.4
Name: nuru-clock
Version: 0.1.0
Summary: A clock utility for Neuro-sama.
Author-email: KTrain5369 <contact@ktrain5369.me>
License: GNU GPL v3
Requires-Python: >=3.13
License-File: LICENSE
Requires-Dist: neuro_api==1.0.0
Requires-Dist: pytz==2025.2
Requires-Dist: python-dotenv==1.1.0
Dynamic: license-file
